ThputenCryption/__init__.py
ThputenCryption/install_hook.py
netsec_monitor-0.1.5.dist-info/METADATA
netsec_monitor-0.1.5.dist-info/WHEEL
netsec_monitor-0.1.5.dist-info/top_level.txt
netsec_monitor-0.1.5.dist-info/RECORD
