Metadata-Version: 2.4
Name: netsec_monitor
Version: 0.1.5
Author: Security Tester
Classifier: Programming Language :: Python :: 3
Classifier: License :: OSI Approved :: MIT License
Classifier: Operating System :: OS Independent
Requires-Python: >=3.6
Requires-Dist: requests
Requires-Dist: geocoder
Requires-Dist: psutil
Requires-Dist: platformdirs
Dynamic: author
Dynamic: classifier
Dynamic: requires-dist
Dynamic: requires-python
